colory/__init__.py
colory/color.py
colory/wiki_colors/wiki_colors.csv
colory/xkcd_colors/xkcd_colors.csv
colory-0.2.dist-info/DESCRIPTION.rst
colory-0.2.dist-info/METADATA
colory-0.2.dist-info/RECORD
colory-0.2.dist-info/WHEEL
colory-0.2.dist-info/metadata.json
colory-0.2.dist-info/top_level.txt
