Metadata-Version: 2.0
Name: colory
Version: 0.2
Summary: A python package to find nearest name of colors using their hex value.
Home-page: https://github.com/apoorvaeternity/colory
Author: Apoorva Pandey
Author-email: apoorvaeternity@gmail.com
License: BSD License
Platform: UNKNOWN
Classifier: Intended Audience :: Developers
Classifier: License :: OSI Approved :: BSD License
Classifier: Operating System :: OS Independent
Classifier: Programming Language :: Python
Requires-Python: >=3
